PDFready/PDFready.py
PDFready/__inti__.py
pdfready-0.1.0.dist-info/licenses/LICENCE
pdfready-0.1.0.dist-info/METADATA
pdfready-0.1.0.dist-info/WHEEL
pdfready-0.1.0.dist-info/top_level.txt
pdfready-0.1.0.dist-info/RECORD
