Metadata-Version: 2.4
Name: PDFready
Version: 0.1.0
Summary: Un lector de archivos PDF en Python
Author-email: Daniel Montañez & Juherles Bravo <gus6gus6gutavo6@gmail.com>
Requires-Python: >=3.7
License-File: LICENCE
Dynamic: license-file
